jaffalearn/__init__.py
jaffalearn/checkpoint.py
jaffalearn/data/__init__.py
jaffalearn/data/cache.py
jaffalearn/data/datasets.py
jaffalearn/data/features.py
jaffalearn/data/loader.py
jaffalearn/data/mixed.py
jaffalearn/engine.py
jaffalearn/logging.py
jaffalearn/system.py
jaffalearn-0.2.0.dist-info/LICENSE
jaffalearn-0.2.0.dist-info/WHEEL
jaffalearn-0.2.0.dist-info/METADATA
jaffalearn-0.2.0.dist-info/RECORD
